{
  "changes": [
    {
      "name": "base_speed",
      "new": 10,
      "old": null,
      "rev": 5,
      "source": "watcher:get",
      "t_ms": 9385
    },
    {
      "name": "cal_l_black",
      "new": 8,
      "old": null,
      "rev": 5,
      "source": "watcher:get",
      "t_ms": 9385
    },
    {
      "name": "cal_l_white",
      "new": 78,
      "old": null,
      "rev": 5,
      "source": "watcher:get",
      "t_ms": 9385
    },
    {
      "name": "cal_r_black",
      "new": 9,
      "old": null,
      "rev": 5,
      "source": "watcher:get",
      "t_ms": 9385
    },
    {
      "name": "cal_r_white",
      "new": 78,
      "old": null,
      "rev": 5,
      "source": "watcher:get",
      "t_ms": 9385
    },
    {
      "name": "deadband",
      "new": 3.0,
      "old": null,
      "rev": 5,
      "source": "watcher:get",
      "t_ms": 9385
    },
    {
      "name": "goal_advance_mm",
      "new": 100,
      "old": null,
      "rev": 5,
      "source": "watcher:get",
      "t_ms": 9385
    },
    {
      "name": "grab_dist_cm",
      "new": 6.0,
      "old": null,
      "rev": 5,
      "source": "watcher:get",
      "t_ms": 9385
    },
    {
      "name": "grip_speed",
      "new": 50,
      "old": null,
      "rev": 5,
      "source": "watcher:get",
      "t_ms": 9385
    },
    {
      "name": "ki",
      "new": 0.06,
      "old": null,
      "rev": 5,
      "source": "watcher:get",
      "t_ms": 9385
    },
    {
      "name": "kp",
      "new": 0.17,
      "old": null,
      "rev": 5,
      "source": "watcher:get",
      "t_ms": 9385
    },
    {
      "name": "left_th_node",
      "new": 35,
      "old": null,
      "rev": 5,
      "source": "watcher:get",
      "t_ms": 9385
    },
    {
      "name": "left_th_steer",
      "new": 66,
      "old": null,
      "rev": 5,
      "source": "watcher:get",
      "t_ms": 9385
    },
    {
      "name": "lost_max_recover",
      "new": 3,
      "old": null,
      "rev": 5,
      "source": "watcher:get",
      "t_ms": 9385
    },
    {
      "name": "lost_persist_ms",
      "new": 200,
      "old": null,
      "rev": 5,
      "source": "watcher:get",
      "t_ms": 9385
    },
    {
      "name": "node_advance_mm",
      "new": 60,
      "old": null,
      "rev": 5,
      "source": "watcher:get",
      "t_ms": 9385
    },
    {
      "name": "node_confirm_ms",
      "new": 40,
      "old": null,
      "rev": 5,
      "source": "watcher:get",
      "t_ms": 9385
    },
    {
      "name": "right_th_node",
      "new": 30,
      "old": null,
      "rev": 5,
      "source": "watcher:get",
      "t_ms": 9385
    },
    {
      "name": "right_th_steer",
      "new": 63,
      "old": null,
      "rev": 5,
      "source": "watcher:get",
      "t_ms": 9385
    },
    {
      "name": "turn_180_factor",
      "new": 0.71,
      "old": null,
      "rev": 5,
      "source": "watcher:get",
      "t_ms": 9385
    },
    {
      "name": "turn_90_factor",
      "new": 0.66,
      "old": null,
      "rev": 5,
      "source": "watcher:get",
      "t_ms": 9385
    },
    {
      "name": "turn_speed",
      "new": 10,
      "old": null,
      "rev": 5,
      "source": "watcher:get",
      "t_ms": 9385
    },
    {
      "name": "cal_l_black",
      "new": 9,
      "old": 8,
      "rev": 9,
      "source": "watcher:get",
      "t_ms": 28343
    },
    {
      "name": "cal_l_white",
      "new": 79,
      "old": 78,
      "rev": 9,
      "source": "watcher:get",
      "t_ms": 28343
    },
    {
      "name": "cal_l_black",
      "new": 8,
      "old": 9,
      "rev": 13,
      "source": "watcher:get",
      "t_ms": 42859
    },
    {
      "name": "cal_l_white",
      "new": 78,
      "old": 79,
      "rev": 13,
      "source": "watcher:get",
      "t_ms": 42859
    },
    {
      "name": "cal_l_white",
      "new": 74,
      "old": 78,
      "rev": 17,
      "source": "watcher:get",
      "t_ms": 58035
    },
    {
      "name": "cal_r_black",
      "new": 7,
      "old": 9,
      "rev": 17,
      "source": "watcher:get",
      "t_ms": 58035
    },
    {
      "name": "cal_r_white",
      "new": 77,
      "old": 78,
      "rev": 17,
      "source": "watcher:get",
      "t_ms": 58035
    },
    {
      "name": "cal_l_black",
      "new": 9,
      "old": 8,
      "rev": 21,
      "source": "watcher:get",
      "t_ms": 70790
    },
    {
      "name": "cal_l_white",
      "new": 78,
      "old": 74,
      "rev": 21,
      "source": "watcher:get",
      "t_ms": 70790
    },
    {
      "name": "cal_r_black",
      "new": 9,
      "old": 7,
      "rev": 21,
      "source": "watcher:get",
      "t_ms": 70790
    },
    {
      "name": "cal_r_white",
      "new": 79,
      "old": 77,
      "rev": 21,
      "source": "watcher:get",
      "t_ms": 70790
    },
    {
      "name": "cal_l_black",
      "new": 8,
      "old": 9,
      "rev": 25,
      "source": "watcher:get",
      "t_ms": 85063
    },
    {
      "name": "cal_l_white",
      "new": 77,
      "old": 78,
      "rev": 25,
      "source": "watcher:get",
      "t_ms": 85063
    },
    {
      "name": "cal_l_white",
      "new": 78,
      "old": 77,
      "rev": 29,
      "source": "watcher:get",
      "t_ms": 91903
    }
  ],
  "initial": {},
  "stage": "final_run3",
  "started": "2026-07-09T09-36-52"
}
